{"arrdelay":18.0,"crsarrtime":1510,"crsdephour":13,"crsdeptime":1310,"crselapsedtime":300.0,"depdelay":3.0,"dist":1947.0,"fldate":"2018-03-18","id":"ATL_LAX_2018-03-18_WN_3362","month":3,"src":"ATL"}
{"arrdelay":7.0,"crsarrtime":1055,"crsdephour":9,"crsdeptime":850,"crselapsedtime":305.0,"depdelay":0.0,"dist":1947.0,"fldate":"2018-03-18","id":"ATL_LAX_2018-03-18_WN_3525","month":3,"src":"ATL"}
{"arrdelay":9.0,"crsarrtime":2215,"crsdephour":20,"crsdeptime":2010,"crselapsedtime":305.0,"depdelay":5.0,"dist":1947.0,"fldate":"2018-03-18","id":"ATL_LAX_2018-03-18_WN_3909","month":3,"src":"ATL"}
{"arrdelay":25.0,"crsarrtime":1535,"crsdephour":14,"crsdeptime":1405,"crselapsedtime":150.0,"depdelay":25.0,"dist":862.0,"fldate":"2018-03-18","id":"DEN_LAX_2018-03-18_WN_2324","month":3,"src":"DEN"}
{"arrdelay":12.0,"crsarrtime":1855,"crsdephour":17,"crsdeptime":1720,"crselapsedtime":155.0,"depdelay":24.0,"dist":862.0,"fldate":"2018-03-18","id":"DEN_LAX_2018-03-18_WN_2604","month":3,"src":"DEN"}
{"arrdelay":1.0,"crsarrtime":1135,"crsdephour":10,"crsdeptime":1000,"crselapsedtime":155.0,"depdelay":1.0,"dist":862.0,"fldate":"2018-03-18","id":"DEN_LAX_2018-03-18_WN_2647","month":3,"src":"DEN"}
{"arrdelay":0.0,"crsarrtime":855,"crsdephour":7,"crsdeptime":720,"crselapsedtime":155.0,"depdelay":0.0,"dist":862.0,"fldate":"2018-03-18","id":"DEN_LAX_2018-03-18_WN_4059","month":3,"src":"DEN"}
{"arrdelay":21.0,"crsarrtime":10,"crsdephour":22,"crsdeptime":2235,"crselapsedtime":155.0,"depdelay":10.0,"dist":862.0,"fldate":"2018-03-18","id":"DEN_LAX_2018-03-18_WN_4061","month":3,"src":"DEN"}
{"arrdelay":0.0,"crsarrtime":1005,"crsdephour":8,"crsdeptime":830,"crselapsedtime":155.0,"depdelay":0.0,"dist":862.0,"fldate":"2018-03-18","id":"DEN_LAX_2018-03-18_WN_4250","month":3,"src":"DEN"}
{"arrdelay":32.0,"crsarrtime":2120,"crsdephour":20,"crsdeptime":1950,"crselapsedtime":150.0,"depdelay":8.0,"dist":862.0,"fldate":"2018-03-18","id":"DEN_LAX_2018-03-18_WN_4905","month":3,"src":"DEN"}
{"arrdelay":8.0,"crsarrtime":1035,"crsdephour":9,"crsdeptime":900,"crselapsedtime":95.0,"depdelay":0.0,"dist":337.0,"fldate":"2018-03-18","id":"SFO_LAX_2018-03-18_WN_1146","month":3,"src":"SFO"}
{"arrdelay":23.0,"crsarrtime":1445,"crsdephour":13,"crsdeptime":1315,"crselapsedtime":90.0,"depdelay":0.0,"dist":337.0,"fldate":"2018-03-18","id":"SFO_LAX_2018-03-18_WN_3973","month":3,"src":"SFO"}
{"arrdelay":44.0,"crsarrtime":1850,"crsdephour":17,"crsdeptime":1725,"crselapsedtime":85.0,"depdelay":12.0,"dist":337.0,"fldate":"2018-03-18","id":"SFO_LAX_2018-03-18_WN_3976","month":3,"src":"SFO"}
{"arrdelay":18.0,"crsarrtime":2300,"crsdephour":21,"crsdeptime":2135,"crselapsedtime":85.0,"depdelay":31.0,"dist":337.0,"fldate":"2018-03-18","id":"SFO_LAX_2018-03-18_WN_3983","month":3,"src":"SFO"}
{"arrdelay":7.0,"crsarrtime":825,"crsdephour":7,"crsdeptime":700,"crselapsedtime":85.0,"depdelay":0.0,"dist":337.0,"fldate":"2018-03-18","id":"SFO_LAX_2018-03-18_WN_4021","month":3,"src":"SFO"}
{"arrdelay":0.0,"crsarrtime":1235,"crsdephour":11,"crsdeptime":1105,"crselapsedtime":90.0,"depdelay":0.0,"dist":337.0,"fldate":"2018-03-18","id":"SFO_LAX_2018-03-18_WN_4024","month":3,"src":"SFO"}
{"arrdelay":0.0,"crsarrtime":1650,"crsdephour":15,"crsdeptime":1520,"crselapsedtime":90.0,"depdelay":0.0,"dist":337.0,"fldate":"2018-03-18","id":"SFO_LAX_2018-03-18_WN_4029","month":3,"src":"SFO"}
{"arrdelay":46.0,"crsarrtime":2100,"crsdephour":19,"crsdeptime":1930,"crselapsedtime":90.0,"depdelay":4.0,"dist":337.0,"fldate":"2018-03-18","id":"SFO_LAX_2018-03-18_WN_4030","month":3,"src":"SFO"}
{"arrdelay":16.0,"crsarrtime":1510,"crsdephour":13,"crsdeptime":1310,"crselapsedtime":300.0,"depdelay":9.0,"dist":1947.0,"fldate":"2018-03-25","id":"ATL_LAX_2018-03-25_WN_3362","month":3,"src":"ATL"}
{"arrdelay":28.0,"crsarrtime":1055,"crsdephour":9,"crsdeptime":850,"crselapsedtime":305.0,"depdelay":30.0,"dist":1947.0,"fldate":"2018-03-25","id":"ATL_LAX_2018-03-25_WN_3525","month":3,"src":"ATL"}
{"arrdelay":9.0,"crsarrtime":2215,"crsdephour":20,"crsdeptime":2010,"crselapsedtime":305.0,"depdelay":3.0,"dist":1947.0,"fldate":"2018-03-25","id":"ATL_LAX_2018-03-25_WN_3909","month":3,"src":"ATL"}
{"arrdelay":4.0,"crsarrtime":1535,"crsdephour":14,"crsdeptime":1405,"crselapsedtime":150.0,"depdelay":0.0,"dist":862.0,"fldate":"2018-03-25","id":"DEN_LAX_2018-03-25_WN_2324","month":3,"src":"DEN"}
{"arrdelay":0.0,"crsarrtime":1855,"crsdephour":17,"crsdeptime":1720,"crselapsedtime":155.0,"depdelay":0.0,"dist":862.0,"fldate":"2018-03-25","id":"DEN_LAX_2018-03-25_WN_2604","month":3,"src":"DEN"}
{"arrdelay":0.0,"crsarrtime":1135,"crsdephour":10,"crsdeptime":1000,"crselapsedtime":155.0,"depdelay":0.0,"dist":862.0,"fldate":"2018-03-25","id":"DEN_LAX_2018-03-25_WN_2647","month":3,"src":"DEN"}
{"arrdelay":0.0,"crsarrtime":855,"crsdephour":7,"crsdeptime":720,"crselapsedtime":155.0,"depdelay":0.0,"dist":862.0,"fldate":"2018-03-25","id":"DEN_LAX_2018-03-25_WN_4059","month":3,"src":"DEN"}
{"arrdelay":5.0,"crsarrtime":10,"crsdephour":22,"crsdeptime":2235,"crselapsedtime":155.0,"depdelay":4.0,"dist":862.0,"fldate":"2018-03-25","id":"DEN_LAX_2018-03-25_WN_4061","month":3,"src":"DEN"}
{"arrdelay":0.0,"crsarrtime":1005,"crsdephour":8,"crsdeptime":830,"crselapsedtime":155.0,"depdelay":0.0,"dist":862.0,"fldate":"2018-03-25","id":"DEN_LAX_2018-03-25_WN_4250","month":3,"src":"DEN"}
{"arrdelay":24.0,"crsarrtime":2120,"crsdephour":20,"crsdeptime":1950,"crselapsedtime":150.0,"depdelay":14.0,"dist":862.0,"fldate":"2018-03-25","id":"DEN_LAX_2018-03-25_WN_4905","month":3,"src":"DEN"}
{"arrdelay":0.0,"crsarrtime":1035,"crsdephour":9,"crsdeptime":900,"crselapsedtime":95.0,"depdelay":4.0,"dist":337.0,"fldate":"2018-03-25","id":"SFO_LAX_2018-03-25_WN_1146","month":3,"src":"SFO"}
{"arrdelay":4.0,"crsarrtime":1445,"crsdephour":13,"crsdeptime":1315,"crselapsedtime":90.0,"depdelay":0.0,"dist":337.0,"fldate":"2018-03-25","id":"SFO_LAX_2018-03-25_WN_3973","month":3,"src":"SFO"}
{"arrdelay":31.0,"crsarrtime":1850,"crsdephour":17,"crsdeptime":1725,"crselapsedtime":85.0,"depdelay":12.0,"dist":337.0,"fldate":"2018-03-25","id":"SFO_LAX_2018-03-25_WN_3976","month":3,"src":"SFO"}
{"arrdelay":26.0,"crsarrtime":2300,"crsdephour":21,"crsdeptime":2135,"crselapsedtime":85.0,"depdelay":32.0,"dist":337.0,"fldate":"2018-03-25","id":"SFO_LAX_2018-03-25_WN_3983","month":3,"src":"SFO"}
{"arrdelay":33.0,"crsarrtime":825,"crsdephour":7,"crsdeptime":700,"crselapsedtime":85.0,"depdelay":30.0,"dist":337.0,"fldate":"2018-03-25","id":"SFO_LAX_2018-03-25_WN_4021","month":3,"src":"SFO"}
{"arrdelay":44.0,"crsarrtime":1235,"crsdephour":11,"crsdeptime":1105,"crselapsedtime":90.0,"depdelay":33.0,"dist":337.0,"fldate":"2018-03-25","id":"SFO_LAX_2018-03-25_WN_4024","month":3,"src":"SFO"}
{"arrdelay":69.0,"crsarrtime":1650,"crsdephour":15,"crsdeptime":1520,"crselapsedtime":90.0,"depdelay":57.0,"dist":337.0,"fldate":"2018-03-25","id":"SFO_LAX_2018-03-25_WN_4029","month":3,"src":"SFO"}
{"arrdelay":86.0,"crsarrtime":2100,"crsdephour":19,"crsdeptime":1930,"crselapsedtime":90.0,"depdelay":99.0,"dist":337.0,"fldate":"2018-03-25","id":"SFO_LAX_2018-03-25_WN_4030","month":3,"src":"SFO"}
{"arrdelay":8.0,"crsarrtime":1345,"crsdephour":12,"crsdeptime":1150,"crselapsedtime":295.0,"depdelay":17.0,"dist":1947.0,"fldate":"2018-05-06","id":"ATL_LAX_2018-05-06_WN_2115","month":5,"src":"ATL"}
{"arrdelay":0.0,"crsarrtime":1050,"crsdephour":9,"crsdeptime":850,"crselapsedtime":300.0,"depdelay":4.0,"dist":1947.0,"fldate":"2018-05-06","id":"ATL_LAX_2018-05-06_WN_2150","month":5,"src":"ATL"}
{"arrdelay":5.0,"crsarrtime":2205,"crsdephour":20,"crsdeptime":2000,"crselapsedtime":305.0,"depdelay":0.0,"dist":1947.0,"fldate":"2018-05-06","id":"ATL_LAX_2018-05-06_WN_702","month":5,"src":"ATL"}
{"arrdelay":0.0,"crsarrtime":2355,"crsdephour":22,"crsdeptime":2225,"crselapsedtime":150.0,"depdelay":0.0,"dist":862.0,"fldate":"2018-05-06","id":"DEN_LAX_2018-05-06_WN_2386","month":5,"src":"DEN"}
{"arrdelay":17.0,"crsarrtime":950,"crsdephour":8,"crsdeptime":820,"crselapsedtime":150.0,"depdelay":18.0,"dist":862.0,"fldate":"2018-05-06","id":"DEN_LAX_2018-05-06_WN_2459","month":5,"src":"DEN"}
{"arrdelay":28.0,"crsarrtime":1110,"crsdephour":9,"crsdeptime":940,"crselapsedtime":150.0,"depdelay":7.0,"dist":862.0,"fldate":"2018-05-06","id":"DEN_LAX_2018-05-06_WN_2463","month":5,"src":"DEN"}
{"arrdelay":0.0,"crsarrtime":1530,"crsdephour":14,"crsdeptime":1400,"crselapsedtime":150.0,"depdelay":0.0,"dist":862.0,"fldate":"2018-05-06","id":"DEN_LAX_2018-05-06_WN_3570","month":5,"src":"DEN"}
{"arrdelay":20.0,"crsarrtime":2120,"crsdephour":20,"crsdeptime":1950,"crselapsedtime":150.0,"depdelay":24.0,"dist":862.0,"fldate":"2018-05-06","id":"DEN_LAX_2018-05-06_WN_3749","month":5,"src":"DEN"}
{"arrdelay":0.0,"crsarrtime":800,"crsdephour":6,"crsdeptime":630,"crselapsedtime":150.0,"depdelay":0.0,"dist":862.0,"fldate":"2018-05-06","id":"DEN_LAX_2018-05-06_WN_3904","month":5,"src":"DEN"}
{"arrdelay":48.0,"crsarrtime":1745,"crsdephour":16,"crsdeptime":1615,"crselapsedtime":150.0,"depdelay":56.0,"dist":862.0,"fldate":"2018-05-06","id":"DEN_LAX_2018-05-06_WN_4933","month":5,"src":"DEN"}
{"arrdelay":0.0,"crsarrtime":700,"crsdephour":5,"crsdeptime":535,"crselapsedtime":85.0,"depdelay":0.0,"dist":337.0,"fldate":"2018-05-06","id":"SFO_LAX_2018-05-06_WN_1245","month":5,"src":"SFO"}
{"arrdelay":105.0,"crsarrtime":1435,"crsdephour":13,"crsdeptime":1305,"crselapsedtime":90.0,"depdelay":39.0,"dist":337.0,"fldate":"2018-05-06","id":"SFO_LAX_2018-05-06_WN_1474","month":5,"src":"SFO"}
{"arrdelay":0.0,"crsarrtime":835,"crsdephour":7,"crsdeptime":705,"crselapsedtime":90.0,"depdelay":2.0,"dist":337.0,"fldate":"2018-05-06","id":"SFO_LAX_2018-05-06_WN_2598","month":5,"src":"SFO"}
{"arrdelay":15.0,"crsarrtime":1245,"crsdephour":11,"crsdeptime":1110,"crselapsedtime":95.0,"depdelay":11.0,"dist":337.0,"fldate":"2018-05-06","id":"SFO_LAX_2018-05-06_WN_2599","month":5,"src":"SFO"}
{"arrdelay":38.0,"crsarrtime":1700,"crsdephour":15,"crsdeptime":1535,"crselapsedtime":85.0,"depdelay":26.0,"dist":337.0,"fldate":"2018-05-06","id":"SFO_LAX_2018-05-06_WN_2603","month":5,"src":"SFO"}
{"arrdelay":41.0,"crsarrtime":2110,"crsdephour":19,"crsdeptime":1940,"crselapsedtime":90.0,"depdelay":38.0,"dist":337.0,"fldate":"2018-05-06","id":"SFO_LAX_2018-05-06_WN_2605","month":5,"src":"SFO"}
{"arrdelay":139.0,"crsarrtime":1850,"crsdephour":17,"crsdeptime":1720,"crselapsedtime":90.0,"depdelay":106.0,"dist":337.0,"fldate":"2018-05-06","id":"SFO_LAX_2018-05-06_WN_2759","month":5,"src":"SFO"}
{"arrdelay":24.0,"crsarrtime":2325,"crsdephour":22,"crsdeptime":2155,"crselapsedtime":90.0,"depdelay":9.0,"dist":337.0,"fldate":"2018-05-06","id":"SFO_LAX_2018-05-06_WN_6190","month":5,"src":"SFO"}
{"arrdelay":15.0,"crsarrtime":1030,"crsdephour":9,"crsdeptime":855,"crselapsedtime":95.0,"depdelay":0.0,"dist":337.0,"fldate":"2018-05-06","id":"SFO_LAX_2018-05-06_WN_6458","month":5,"src":"SFO"}
{"arrdelay":0.0,"crsarrtime":1345,"crsdephour":12,"crsdeptime":1150,"crselapsedtime":295.0,"depdelay":0.0,"dist":1947.0,"fldate":"2018-05-13","id":"ATL_LAX_2018-05-13_WN_2115","month":5,"src":"ATL"}
{"arrdelay":0.0,"crsarrtime":1050,"crsdephour":9,"crsdeptime":850,"crselapsedtime":300.0,"depdelay":11.0,"dist":1947.0,"fldate":"2018-05-13","id":"ATL_LAX_2018-05-13_WN_2150","month":5,"src":"ATL"}
{"arrdelay":0.0,"crsarrtime":2205,"crsdephour":20,"crsdeptime":2000,"crselapsedtime":305.0,"depdelay":18.0,"dist":1947.0,"fldate":"2018-05-13","id":"ATL_LAX_2018-05-13_WN_702","month":5,"src":"ATL"}
{"arrdelay":0.0,"crsarrtime":2355,"crsdephour":22,"crsdeptime":2225,"crselapsedtime":150.0,"depdelay":0.0,"dist":862.0,"fldate":"2018-05-13","id":"DEN_LAX_2018-05-13_WN_2386","month":5,"src":"DEN"}
{"arrdelay":8.0,"crsarrtime":950,"crsdephour":8,"crsdeptime":820,"crselapsedtime":150.0,"depdelay":3.0,"dist":862.0,"fldate":"2018-05-13","id":"DEN_LAX_2018-05-13_WN_2459","month":5,"src":"DEN"}
{"arrdelay":8.0,"crsarrtime":1110,"crsdephour":9,"crsdeptime":940,"crselapsedtime":150.0,"depdelay":9.0,"dist":862.0,"fldate":"2018-05-13","id":"DEN_LAX_2018-05-13_WN_2463","month":5,"src":"DEN"}
{"arrdelay":26.0,"crsarrtime":1530,"crsdephour":14,"crsdeptime":1400,"crselapsedtime":150.0,"depdelay":31.0,"dist":862.0,"fldate":"2018-05-13","id":"DEN_LAX_2018-05-13_WN_3570","month":5,"src":"DEN"}
{"arrdelay":0.0,"crsarrtime":2120,"crsdephour":20,"crsdeptime":1950,"crselapsedtime":150.0,"depdelay":4.0,"dist":862.0,"fldate":"2018-05-13","id":"DEN_LAX_2018-05-13_WN_3749","month":5,"src":"DEN"}
{"arrdelay":0.0,"crsarrtime":800,"crsdephour":6,"crsdeptime":630,"crselapsedtime":150.0,"depdelay":0.0,"dist":862.0,"fldate":"2018-05-13","id":"DEN_LAX_2018-05-13_WN_3904","month":5,"src":"DEN"}
{"arrdelay":4.0,"crsarrtime":1745,"crsdephour":16,"crsdeptime":1615,"crselapsedtime":150.0,"depdelay":9.0,"dist":862.0,"fldate":"2018-05-13","id":"DEN_LAX_2018-05-13_WN_4933","month":5,"src":"DEN"}
