{"arrdelay":67.0,"crsarrtime":2114,"crsdephour":18,"crsdeptime":1829,"crselapsedtime":345.0,"depdelay":80.0,"dist":2296.0,"fldate":"2018-05-18","id":"CLT_SFO_2018-05-18_AA_1799","month":5,"src":"CLT"}
{"arrdelay":12.0,"crsarrtime":1921,"crsdephour":16,"crsdeptime":1634,"crselapsedtime":347.0,"depdelay":20.0,"dist":2296.0,"fldate":"2018-05-18","id":"CLT_SFO_2018-05-18_AA_1816","month":5,"src":"CLT"}
{"arrdelay":10.0,"crsarrtime":1742,"crsdephour":15,"crsdeptime":1504,"crselapsedtime":338.0,"depdelay":33.0,"dist":2296.0,"fldate":"2018-05-18","id":"CLT_SFO_2018-05-18_AA_2019","month":5,"src":"CLT"}
{"arrdelay":179.0,"crsarrtime":2236,"crsdephour":20,"crsdeptime":1959,"crselapsedtime":337.0,"depdelay":173.0,"dist":2296.0,"fldate":"2018-05-18","id":"CLT_SFO_2018-05-18_AA_503","month":5,"src":"CLT"}
{"arrdelay":6.0,"crsarrtime":1001,"crsdephour":7,"crsdeptime":730,"crselapsedtime":331.0,"depdelay":7.0,"dist":2296.0,"fldate":"2018-05-18","id":"CLT_SFO_2018-05-18_AA_662","month":5,"src":"CLT"}
{"arrdelay":0.0,"crsarrtime":1848,"crsdephour":17,"crsdeptime":1655,"crselapsedtime":233.0,"depdelay":6.0,"dist":1464.0,"fldate":"2018-05-18","id":"DFW_SFO_2018-05-18_AA_1083","month":5,"src":"DFW"}
{"arrdelay":4.0,"crsarrtime":2038,"crsdephour":18,"crsdeptime":1840,"crselapsedtime":238.0,"depdelay":0.0,"dist":1464.0,"fldate":"2018-05-18","id":"DFW_SFO_2018-05-18_AA_1393","month":5,"src":"DFW"}
{"arrdelay":0.0,"crsarrtime":906,"crsdephour":7,"crsdeptime":715,"crselapsedtime":231.0,"depdelay":0.0,"dist":1464.0,"fldate":"2018-05-18","id":"DFW_SFO_2018-05-18_AA_159","month":5,"src":"DFW"}
{"arrdelay":58.0,"crsarrtime":1108,"crsdephour":9,"crsdeptime":907,"crselapsedtime":241.0,"depdelay":58.0,"dist":1464.0,"fldate":"2018-05-18","id":"DFW_SFO_2018-05-18_AA_2238","month":5,"src":"DFW"}
{"arrdelay":0.0,"crsarrtime":1635,"crsdephour":14,"crsdeptime":1440,"crselapsedtime":235.0,"depdelay":3.0,"dist":1464.0,"fldate":"2018-05-18","id":"DFW_SFO_2018-05-18_AA_2352","month":5,"src":"DFW"}
{"arrdelay":76.0,"crsarrtime":1256,"crsdephour":11,"crsdeptime":1055,"crselapsedtime":241.0,"depdelay":82.0,"dist":1464.0,"fldate":"2018-05-18","id":"DFW_SFO_2018-05-18_AA_2701","month":5,"src":"DFW"}
{"arrdelay":0.0,"crsarrtime":1457,"crsdephour":13,"crsdeptime":1302,"crselapsedtime":235.0,"depdelay":0.0,"dist":1464.0,"fldate":"2018-05-18","id":"DFW_SFO_2018-05-18_AA_349","month":5,"src":"DFW"}
{"arrdelay":41.0,"crsarrtime":15,"crsdephour":22,"crsdeptime":2220,"crselapsedtime":235.0,"depdelay":30.0,"dist":1464.0,"fldate":"2018-05-18","id":"DFW_SFO_2018-05-18_AA_417","month":5,"src":"DFW"}
{"arrdelay":5.0,"crsarrtime":2239,"crsdephour":20,"crsdeptime":2045,"crselapsedtime":234.0,"depdelay":23.0,"dist":1464.0,"fldate":"2018-05-18","id":"DFW_SFO_2018-05-18_AA_85","month":5,"src":"DFW"}
{"arrdelay":0.0,"crsarrtime":1150,"crsdephour":8,"crsdeptime":830,"crselapsedtime":380.0,"depdelay":10.0,"dist":2585.0,"fldate":"2018-05-18","id":"MIA_SFO_2018-05-18_AA_167","month":5,"src":"MIA"}
{"arrdelay":50.0,"crsarrtime":2259,"crsdephour":19,"crsdeptime":1936,"crselapsedtime":383.0,"depdelay":71.0,"dist":2585.0,"fldate":"2018-05-18","id":"MIA_SFO_2018-05-18_AA_2647","month":5,"src":"MIA"}
{"arrdelay":104.0,"crsarrtime":2125,"crsdephour":18,"crsdeptime":1805,"crselapsedtime":380.0,"depdelay":119.0,"dist":2585.0,"fldate":"2018-05-18","id":"MIA_SFO_2018-05-18_AA_2669","month":5,"src":"MIA"}
{"arrdelay":98.0,"crsarrtime":57,"crsdephour":21,"crsdeptime":2135,"crselapsedtime":382.0,"depdelay":142.0,"dist":2585.0,"fldate":"2018-05-18","id":"MIA_SFO_2018-05-18_AA_555","month":5,"src":"MIA"}
{"arrdelay":0.0,"crsarrtime":1005,"crsdephour":7,"crsdeptime":725,"crselapsedtime":280.0,"depdelay":2.0,"dist":1846.0,"fldate":"2018-05-18","id":"ORD_SFO_2018-05-18_AA_1290","month":5,"src":"ORD"}
{"arrdelay":45.0,"crsarrtime":2313,"crsdephour":20,"crsdeptime":2030,"crselapsedtime":283.0,"depdelay":49.0,"dist":1846.0,"fldate":"2018-05-18","id":"ORD_SFO_2018-05-18_AA_1522","month":5,"src":"ORD"}
{"arrdelay":76.0,"crsarrtime":1306,"crsdephour":10,"crsdeptime":1025,"crselapsedtime":281.0,"depdelay":93.0,"dist":1846.0,"fldate":"2018-05-18","id":"ORD_SFO_2018-05-18_AA_2234","month":5,"src":"ORD"}
{"arrdelay":5.0,"crsarrtime":1710,"crsdephour":14,"crsdeptime":1430,"crselapsedtime":280.0,"depdelay":0.0,"dist":1846.0,"fldate":"2018-05-18","id":"ORD_SFO_2018-05-18_AA_2639","month":5,"src":"ORD"}
{"arrdelay":96.0,"crsarrtime":1949,"crsdephour":17,"crsdeptime":1705,"crselapsedtime":284.0,"depdelay":90.0,"dist":1846.0,"fldate":"2018-05-18","id":"ORD_SFO_2018-05-18_AA_2798","month":5,"src":"ORD"}
{"arrdelay":35.0,"crsarrtime":2114,"crsdephour":18,"crsdeptime":1829,"crselapsedtime":345.0,"depdelay":24.0,"dist":2296.0,"fldate":"2018-05-25","id":"CLT_SFO_2018-05-25_AA_1799","month":5,"src":"CLT"}
{"arrdelay":18.0,"crsarrtime":1921,"crsdephour":16,"crsdeptime":1634,"crselapsedtime":347.0,"depdelay":42.0,"dist":2296.0,"fldate":"2018-05-25","id":"CLT_SFO_2018-05-25_AA_1816","month":5,"src":"CLT"}
{"arrdelay":0.0,"crsarrtime":1742,"crsdephour":15,"crsdeptime":1504,"crselapsedtime":338.0,"depdelay":0.0,"dist":2296.0,"fldate":"2018-05-25","id":"CLT_SFO_2018-05-25_AA_2019","month":5,"src":"CLT"}
{"arrdelay":21.0,"crsarrtime":1157,"crsdephour":9,"crsdeptime":920,"crselapsedtime":337.0,"depdelay":1.0,"dist":2296.0,"fldate":"2018-05-25","id":"CLT_SFO_2018-05-25_AA_461","month":5,"src":"CLT"}
{"arrdelay":47.0,"crsarrtime":2236,"crsdephour":20,"crsdeptime":1959,"crselapsedtime":337.0,"depdelay":42.0,"dist":2296.0,"fldate":"2018-05-25","id":"CLT_SFO_2018-05-25_AA_503","month":5,"src":"CLT"}
{"arrdelay":0.0,"crsarrtime":1001,"crsdephour":7,"crsdeptime":730,"crselapsedtime":331.0,"depdelay":3.0,"dist":2296.0,"fldate":"2018-05-25","id":"CLT_SFO_2018-05-25_AA_662","month":5,"src":"CLT"}
{"arrdelay":0.0,"crsarrtime":1848,"crsdephour":17,"crsdeptime":1655,"crselapsedtime":233.0,"depdelay":0.0,"dist":1464.0,"fldate":"2018-05-25","id":"DFW_SFO_2018-05-25_AA_1083","month":5,"src":"DFW"}
{"arrdelay":57.0,"crsarrtime":2038,"crsdephour":18,"crsdeptime":1840,"crselapsedtime":238.0,"depdelay":52.0,"dist":1464.0,"fldate":"2018-05-25","id":"DFW_SFO_2018-05-25_AA_1393","month":5,"src":"DFW"}
{"arrdelay":10.0,"crsarrtime":906,"crsdephour":7,"crsdeptime":715,"crselapsedtime":231.0,"depdelay":31.0,"dist":1464.0,"fldate":"2018-05-25","id":"DFW_SFO_2018-05-25_AA_159","month":5,"src":"DFW"}
{"arrdelay":45.0,"crsarrtime":1108,"crsdephour":9,"crsdeptime":907,"crselapsedtime":241.0,"depdelay":35.0,"dist":1464.0,"fldate":"2018-05-25","id":"DFW_SFO_2018-05-25_AA_2238","month":5,"src":"DFW"}
{"arrdelay":0.0,"crsarrtime":1635,"crsdephour":14,"crsdeptime":1440,"crselapsedtime":235.0,"depdelay":0.0,"dist":1464.0,"fldate":"2018-05-25","id":"DFW_SFO_2018-05-25_AA_2352","month":5,"src":"DFW"}
{"arrdelay":22.0,"crsarrtime":1256,"crsdephour":11,"crsdeptime":1055,"crselapsedtime":241.0,"depdelay":32.0,"dist":1464.0,"fldate":"2018-05-25","id":"DFW_SFO_2018-05-25_AA_2701","month":5,"src":"DFW"}
{"arrdelay":21.0,"crsarrtime":1457,"crsdephour":13,"crsdeptime":1302,"crselapsedtime":235.0,"depdelay":0.0,"dist":1464.0,"fldate":"2018-05-25","id":"DFW_SFO_2018-05-25_AA_349","month":5,"src":"DFW"}
{"arrdelay":41.0,"crsarrtime":15,"crsdephour":22,"crsdeptime":2220,"crselapsedtime":235.0,"depdelay":60.0,"dist":1464.0,"fldate":"2018-05-25","id":"DFW_SFO_2018-05-25_AA_417","month":5,"src":"DFW"}
{"arrdelay":86.0,"crsarrtime":2239,"crsdephour":20,"crsdeptime":2045,"crselapsedtime":234.0,"depdelay":82.0,"dist":1464.0,"fldate":"2018-05-25","id":"DFW_SFO_2018-05-25_AA_85","month":5,"src":"DFW"}
{"arrdelay":0.0,"crsarrtime":1150,"crsdephour":8,"crsdeptime":830,"crselapsedtime":380.0,"depdelay":0.0,"dist":2585.0,"fldate":"2018-05-25","id":"MIA_SFO_2018-05-25_AA_167","month":5,"src":"MIA"}
{"arrdelay":60.0,"crsarrtime":2259,"crsdephour":19,"crsdeptime":1936,"crselapsedtime":383.0,"depdelay":66.0,"dist":2585.0,"fldate":"2018-05-25","id":"MIA_SFO_2018-05-25_AA_2647","month":5,"src":"MIA"}
{"arrdelay":26.0,"crsarrtime":2125,"crsdephour":18,"crsdeptime":1805,"crselapsedtime":380.0,"depdelay":25.0,"dist":2585.0,"fldate":"2018-05-25","id":"MIA_SFO_2018-05-25_AA_2669","month":5,"src":"MIA"}
{"arrdelay":11.0,"crsarrtime":57,"crsdephour":21,"crsdeptime":2135,"crselapsedtime":382.0,"depdelay":23.0,"dist":2585.0,"fldate":"2018-05-25","id":"MIA_SFO_2018-05-25_AA_555","month":5,"src":"MIA"}
{"arrdelay":0.0,"crsarrtime":1005,"crsdephour":7,"crsdeptime":725,"crselapsedtime":280.0,"depdelay":0.0,"dist":1846.0,"fldate":"2018-05-25","id":"ORD_SFO_2018-05-25_AA_1290","month":5,"src":"ORD"}
{"arrdelay":32.0,"crsarrtime":2313,"crsdephour":20,"crsdeptime":2030,"crselapsedtime":283.0,"depdelay":8.0,"dist":1846.0,"fldate":"2018-05-25","id":"ORD_SFO_2018-05-25_AA_1522","month":5,"src":"ORD"}
{"arrdelay":34.0,"crsarrtime":1306,"crsdephour":10,"crsdeptime":1025,"crselapsedtime":281.0,"depdelay":31.0,"dist":1846.0,"fldate":"2018-05-25","id":"ORD_SFO_2018-05-25_AA_2234","month":5,"src":"ORD"}
{"arrdelay":14.0,"crsarrtime":1710,"crsdephour":14,"crsdeptime":1430,"crselapsedtime":280.0,"depdelay":0.0,"dist":1846.0,"fldate":"2018-05-25","id":"ORD_SFO_2018-05-25_AA_2639","month":5,"src":"ORD"}
{"arrdelay":27.0,"crsarrtime":1949,"crsdephour":17,"crsdeptime":1705,"crselapsedtime":284.0,"depdelay":41.0,"dist":1846.0,"fldate":"2018-05-25","id":"ORD_SFO_2018-05-25_AA_2798","month":5,"src":"ORD"}
{"arrdelay":35.0,"crsarrtime":2114,"crsdephour":18,"crsdeptime":1829,"crselapsedtime":345.0,"depdelay":0.0,"dist":2296.0,"fldate":"2018-06-01","id":"CLT_SFO_2018-06-01_AA_1799","month":6,"src":"CLT"}
{"arrdelay":22.0,"crsarrtime":1921,"crsdephour":16,"crsdeptime":1634,"crselapsedtime":347.0,"depdelay":46.0,"dist":2296.0,"fldate":"2018-06-01","id":"CLT_SFO_2018-06-01_AA_1816","month":6,"src":"CLT"}
{"arrdelay":5.0,"crsarrtime":1742,"crsdephour":15,"crsdeptime":1504,"crselapsedtime":338.0,"depdelay":26.0,"dist":2296.0,"fldate":"2018-06-01","id":"CLT_SFO_2018-06-01_AA_2019","month":6,"src":"CLT"}
{"arrdelay":78.0,"crsarrtime":1157,"crsdephour":9,"crsdeptime":920,"crselapsedtime":337.0,"depdelay":39.0,"dist":2296.0,"fldate":"2018-06-01","id":"CLT_SFO_2018-06-01_AA_461","month":6,"src":"CLT"}
{"arrdelay":94.0,"crsarrtime":2236,"crsdephour":20,"crsdeptime":1959,"crselapsedtime":337.0,"depdelay":105.0,"dist":2296.0,"fldate":"2018-06-01","id":"CLT_SFO_2018-06-01_AA_503","month":6,"src":"CLT"}
{"arrdelay":1.0,"crsarrtime":1001,"crsdephour":7,"crsdeptime":730,"crselapsedtime":331.0,"depdelay":6.0,"dist":2296.0,"fldate":"2018-06-01","id":"CLT_SFO_2018-06-01_AA_662","month":6,"src":"CLT"}
{"arrdelay":0.0,"crsarrtime":1848,"crsdephour":17,"crsdeptime":1655,"crselapsedtime":233.0,"depdelay":0.0,"dist":1464.0,"fldate":"2018-06-01","id":"DFW_SFO_2018-06-01_AA_1083","month":6,"src":"DFW"}
{"arrdelay":0.0,"crsarrtime":2038,"crsdephour":18,"crsdeptime":1840,"crselapsedtime":238.0,"depdelay":1.0,"dist":1464.0,"fldate":"2018-06-01","id":"DFW_SFO_2018-06-01_AA_1393","month":6,"src":"DFW"}
{"arrdelay":0.0,"crsarrtime":906,"crsdephour":7,"crsdeptime":715,"crselapsedtime":231.0,"depdelay":0.0,"dist":1464.0,"fldate":"2018-06-01","id":"DFW_SFO_2018-06-01_AA_159","month":6,"src":"DFW"}
{"arrdelay":17.0,"crsarrtime":1108,"crsdephour":9,"crsdeptime":907,"crselapsedtime":241.0,"depdelay":1.0,"dist":1464.0,"fldate":"2018-06-01","id":"DFW_SFO_2018-06-01_AA_2238","month":6,"src":"DFW"}
{"arrdelay":0.0,"crsarrtime":1635,"crsdephour":14,"crsdeptime":1440,"crselapsedtime":235.0,"depdelay":0.0,"dist":1464.0,"fldate":"2018-06-01","id":"DFW_SFO_2018-06-01_AA_2352","month":6,"src":"DFW"}
{"arrdelay":0.0,"crsarrtime":1256,"crsdephour":11,"crsdeptime":1055,"crselapsedtime":241.0,"depdelay":0.0,"dist":1464.0,"fldate":"2018-06-01","id":"DFW_SFO_2018-06-01_AA_2701","month":6,"src":"DFW"}
{"arrdelay":0.0,"crsarrtime":1457,"crsdephour":13,"crsdeptime":1302,"crselapsedtime":235.0,"depdelay":0.0,"dist":1464.0,"fldate":"2018-06-01","id":"DFW_SFO_2018-06-01_AA_349","month":6,"src":"DFW"}
{"arrdelay":66.0,"crsarrtime":15,"crsdephour":22,"crsdeptime":2220,"crselapsedtime":235.0,"depdelay":82.0,"dist":1464.0,"fldate":"2018-06-01","id":"DFW_SFO_2018-06-01_AA_417","month":6,"src":"DFW"}
{"arrdelay":0.0,"crsarrtime":2239,"crsdephour":20,"crsdeptime":2045,"crselapsedtime":234.0,"depdelay":7.0,"dist":1464.0,"fldate":"2018-06-01","id":"DFW_SFO_2018-06-01_AA_85","month":6,"src":"DFW"}
{"arrdelay":0.0,"crsarrtime":1150,"crsdephour":8,"crsdeptime":830,"crselapsedtime":380.0,"depdelay":0.0,"dist":2585.0,"fldate":"2018-06-01","id":"MIA_SFO_2018-06-01_AA_167","month":6,"src":"MIA"}
{"arrdelay":0.0,"crsarrtime":2259,"crsdephour":19,"crsdeptime":1936,"crselapsedtime":383.0,"depdelay":0.0,"dist":2585.0,"fldate":"2018-06-01","id":"MIA_SFO_2018-06-01_AA_2647","month":6,"src":"MIA"}
{"arrdelay":0.0,"crsarrtime":2125,"crsdephour":18,"crsdeptime":1805,"crselapsedtime":380.0,"depdelay":0.0,"dist":2585.0,"fldate":"2018-06-01","id":"MIA_SFO_2018-06-01_AA_2669","month":6,"src":"MIA"}
{"arrdelay":0.0,"crsarrtime":57,"crsdephour":21,"crsdeptime":2135,"crselapsedtime":382.0,"depdelay":0.0,"dist":2585.0,"fldate":"2018-06-01","id":"MIA_SFO_2018-06-01_AA_555","month":6,"src":"MIA"}
{"arrdelay":0.0,"crsarrtime":1005,"crsdephour":7,"crsdeptime":725,"crselapsedtime":280.0,"depdelay":0.0,"dist":1846.0,"fldate":"2018-06-01","id":"ORD_SFO_2018-06-01_AA_1290","month":6,"src":"ORD"}
{"arrdelay":0.0,"crsarrtime":2313,"crsdephour":20,"crsdeptime":2030,"crselapsedtime":283.0,"depdelay":0.0,"dist":1846.0,"fldate":"2018-06-01","id":"ORD_SFO_2018-06-01_AA_1522","month":6,"src":"ORD"}
{"arrdelay":20.0,"crsarrtime":1306,"crsdephour":10,"crsdeptime":1025,"crselapsedtime":281.0,"depdelay":0.0,"dist":1846.0,"fldate":"2018-06-01","id":"ORD_SFO_2018-06-01_AA_2234","month":6,"src":"ORD"}
{"arrdelay":0.0,"crsarrtime":1710,"crsdephour":14,"crsdeptime":1430,"crselapsedtime":280.0,"depdelay":1.0,"dist":1846.0,"fldate":"2018-06-01","id":"ORD_SFO_2018-06-01_AA_2639","month":6,"src":"ORD"}
{"arrdelay":23.0,"crsarrtime":1949,"crsdephour":17,"crsdeptime":1705,"crselapsedtime":284.0,"depdelay":49.0,"dist":1846.0,"fldate":"2018-06-01","id":"ORD_SFO_2018-06-01_AA_2798","month":6,"src":"ORD"}
{"arrdelay":15.0,"crsarrtime":1900,"crsdephour":16,"crsdeptime":1630,"crselapsedtime":330.0,"depdelay":27.0,"dist":2296.0,"fldate":"2018-06-08","id":"CLT_SFO_2018-06-08_AA_1659","month":6,"src":"CLT"}
{"arrdelay":29.0,"crsarrtime":2257,"crsdephour":20,"crsdeptime":2030,"crselapsedtime":327.0,"depdelay":44.0,"dist":2296.0,"fldate":"2018-06-08","id":"CLT_SFO_2018-06-08_AA_1873","month":6,"src":"CLT"}
{"arrdelay":0.0,"crsarrtime":1208,"crsdephour":9,"crsdeptime":940,"crselapsedtime":328.0,"depdelay":3.0,"dist":2296.0,"fldate":"2018-06-08","id":"CLT_SFO_2018-06-08_AA_1956","month":6,"src":"CLT"}
{"arrdelay":0.0,"crsarrtime":1724,"crsdephour":15,"crsdeptime":1459,"crselapsedtime":325.0,"depdelay":0.0,"dist":2296.0,"fldate":"2018-06-08","id":"CLT_SFO_2018-06-08_AA_2061","month":6,"src":"CLT"}
{"arrdelay":0.0,"crsarrtime":2059,"crsdephour":18,"crsdeptime":1829,"crselapsedtime":330.0,"depdelay":0.0,"dist":2296.0,"fldate":"2018-06-08","id":"CLT_SFO_2018-06-08_AA_2151","month":6,"src":"CLT"}
{"arrdelay":0.0,"crsarrtime":957,"crsdephour":7,"crsdeptime":735,"crselapsedtime":322.0,"depdelay":0.0,"dist":2296.0,"fldate":"2018-06-08","id":"CLT_SFO_2018-06-08_AA_785","month":6,"src":"CLT"}
{"arrdelay":0.0,"crsarrtime":1834,"crsdephour":17,"crsdeptime":1655,"crselapsedtime":219.0,"depdelay":0.0,"dist":1464.0,"fldate":"2018-06-08","id":"DFW_SFO_2018-06-08_AA_1175","month":6,"src":"DFW"}
{"arrdelay":102.0,"crsarrtime":1058,"crsdephour":9,"crsdeptime":910,"crselapsedtime":228.0,"depdelay":98.0,"dist":1464.0,"fldate":"2018-06-08","id":"DFW_SFO_2018-06-08_AA_1260","month":6,"src":"DFW"}
{"arrdelay":51.0,"crsarrtime":1439,"crsdephour":13,"crsdeptime":1259,"crselapsedtime":220.0,"depdelay":64.0,"dist":1464.0,"fldate":"2018-06-08","id":"DFW_SFO_2018-06-08_AA_139","month":6,"src":"DFW"}
{"arrdelay":159.0,"crsarrtime":2021,"crsdephour":18,"crsdeptime":1840,"crselapsedtime":221.0,"depdelay":143.0,"dist":1464.0,"fldate":"2018-06-08","id":"DFW_SFO_2018-06-08_AA_1430","month":6,"src":"DFW"}
{"arrdelay":127.0,"crsarrtime":855,"crsdephour":7,"crsdeptime":715,"crselapsedtime":220.0,"depdelay":143.0,"dist":1464.0,"fldate":"2018-06-08","id":"DFW_SFO_2018-06-08_AA_152","month":6,"src":"DFW"}
{"arrdelay":18.0,"crsarrtime":1256,"crsdephour":11,"crsdeptime":1110,"crselapsedtime":226.0,"depdelay":23.0,"dist":1464.0,"fldate":"2018-06-08","id":"DFW_SFO_2018-06-08_AA_2248","month":6,"src":"DFW"}
{"arrdelay":18.0,"crsarrtime":1630,"crsdephour":15,"crsdeptime":1450,"crselapsedtime":220.0,"depdelay":21.0,"dist":1464.0,"fldate":"2018-06-08","id":"DFW_SFO_2018-06-08_AA_2683","month":6,"src":"DFW"}
{"arrdelay":90.0,"crsarrtime":2,"crsdephour":22,"crsdeptime":2220,"crselapsedtime":222.0,"depdelay":100.0,"dist":1464.0,"fldate":"2018-06-08","id":"DFW_SFO_2018-06-08_AA_446","month":6,"src":"DFW"}
{"arrdelay":118.0,"crsarrtime":2227,"crsdephour":20,"crsdeptime":2045,"crselapsedtime":222.0,"depdelay":127.0,"dist":1464.0,"fldate":"2018-06-08","id":"DFW_SFO_2018-06-08_AA_75","month":6,"src":"DFW"}
{"arrdelay":38.0,"crsarrtime":36,"crsdephour":21,"crsdeptime":2135,"crselapsedtime":361.0,"depdelay":0.0,"dist":2585.0,"fldate":"2018-06-08","id":"MIA_SFO_2018-06-08_AA_2280","month":6,"src":"MIA"}
{"arrdelay":14.0,"crsarrtime":2254,"crsdephour":20,"crsdeptime":1950,"crselapsedtime":364.0,"depdelay":17.0,"dist":2585.0,"fldate":"2018-06-08","id":"MIA_SFO_2018-06-08_AA_2421","month":6,"src":"MIA"}
{"arrdelay":60.0,"crsarrtime":2058,"crsdephour":18,"crsdeptime":1755,"crselapsedtime":363.0,"depdelay":60.0,"dist":2585.0,"fldate":"2018-06-08","id":"MIA_SFO_2018-06-08_AA_2688","month":6,"src":"MIA"}
{"arrdelay":0.0,"crsarrtime":1129,"crsdephour":8,"crsdeptime":831,"crselapsedtime":358.0,"depdelay":0.0,"dist":2585.0,"fldate":"2018-06-08","id":"MIA_SFO_2018-06-08_AA_383","month":6,"src":"MIA"}
{"arrdelay":4.0,"crsarrtime":2308,"crsdephour":20,"crsdeptime":2030,"crselapsedtime":278.0,"depdelay":10.0,"dist":1846.0,"fldate":"2018-06-08","id":"ORD_SFO_2018-06-08_AA_1253","month":6,"src":"ORD"}
{"arrdelay":111.0,"crsarrtime":1502,"crsdephour":12,"crsdeptime":1225,"crselapsedtime":277.0,"depdelay":105.0,"dist":1846.0,"fldate":"2018-06-08","id":"ORD_SFO_2018-06-08_AA_1470","month":6,"src":"ORD"}
{"arrdelay":80.0,"crsarrtime":1300,"crsdephour":10,"crsdeptime":1025,"crselapsedtime":275.0,"depdelay":52.0,"dist":1846.0,"fldate":"2018-06-08","id":"ORD_SFO_2018-06-08_AA_2634","month":6,"src":"ORD"}
{"arrdelay":103.0,"crsarrtime":1716,"crsdephour":14,"crsdeptime":1444,"crselapsedtime":272.0,"depdelay":101.0,"dist":1846.0,"fldate":"2018-06-08","id":"ORD_SFO_2018-06-08_AA_2639","month":6,"src":"ORD"}
{"arrdelay":72.0,"crsarrtime":2005,"crsdephour":17,"crsdeptime":1730,"crselapsedtime":275.0,"depdelay":62.0,"dist":1846.0,"fldate":"2018-06-08","id":"ORD_SFO_2018-06-08_AA_2798","month":6,"src":"ORD"}
{"arrdelay":14.0,"crsarrtime":947,"crsdephour":7,"crsdeptime":719,"crselapsedtime":268.0,"depdelay":15.0,"dist":1846.0,"fldate":"2018-06-08","id":"ORD_SFO_2018-06-08_AA_345","month":6,"src":"ORD"}
