{"arrdelay":0.0,"crsarrtime":945,"crsdephour":6,"crsdeptime":625,"crselapsedtime":380.0,"depdelay":2.0,"dist":2611.0,"fldate":"2018-07-18","id":"BOS_LAX_2018-07-18_UA_1820","month":7,"src":"BOS"}
{"arrdelay":0.0,"crsarrtime":1235,"crsdephour":9,"crsdeptime":910,"crselapsedtime":385.0,"depdelay":0.0,"dist":2611.0,"fldate":"2018-07-18","id":"BOS_LAX_2018-07-18_UA_2145","month":7,"src":"BOS"}
{"arrdelay":0.0,"crsarrtime":2034,"crsdephour":17,"crsdeptime":1701,"crselapsedtime":393.0,"depdelay":0.0,"dist":2611.0,"fldate":"2018-07-18","id":"BOS_LAX_2018-07-18_UA_717","month":7,"src":"BOS"}
{"arrdelay":0.0,"crsarrtime":930,"crsdephour":8,"crsdeptime":758,"crselapsedtime":152.0,"depdelay":0.0,"dist":862.0,"fldate":"2018-07-18","id":"DEN_LAX_2018-07-18_UA_1093","month":7,"src":"DEN"}
{"arrdelay":0.0,"crsarrtime":2020,"crsdephour":19,"crsdeptime":1855,"crselapsedtime":145.0,"depdelay":0.0,"dist":862.0,"fldate":"2018-07-18","id":"DEN_LAX_2018-07-18_UA_1613","month":7,"src":"DEN"}
{"arrdelay":0.0,"crsarrtime":1409,"crsdephour":12,"crsdeptime":1244,"crselapsedtime":145.0,"depdelay":0.0,"dist":862.0,"fldate":"2018-07-18","id":"DEN_LAX_2018-07-18_UA_2091","month":7,"src":"DEN"}
{"arrdelay":31.0,"crsarrtime":708,"crsdephour":5,"crsdeptime":545,"crselapsedtime":143.0,"depdelay":33.0,"dist":862.0,"fldate":"2018-07-18","id":"DEN_LAX_2018-07-18_UA_2186","month":7,"src":"DEN"}
{"arrdelay":0.0,"crsarrtime":1239,"crsdephour":11,"crsdeptime":1115,"crselapsedtime":144.0,"depdelay":0.0,"dist":862.0,"fldate":"2018-07-18","id":"DEN_LAX_2018-07-18_UA_420","month":7,"src":"DEN"}
{"arrdelay":2.0,"crsarrtime":1703,"crsdephour":15,"crsdeptime":1535,"crselapsedtime":148.0,"depdelay":9.0,"dist":862.0,"fldate":"2018-07-18","id":"DEN_LAX_2018-07-18_UA_481","month":7,"src":"DEN"}
{"arrdelay":2.0,"crsarrtime":1540,"crsdephour":14,"crsdeptime":1415,"crselapsedtime":145.0,"depdelay":1.0,"dist":862.0,"fldate":"2018-07-18","id":"DEN_LAX_2018-07-18_UA_744","month":7,"src":"DEN"}
{"arrdelay":0.0,"crsarrtime":13,"crsdephour":23,"crsdeptime":2250,"crselapsedtime":143.0,"depdelay":0.0,"dist":862.0,"fldate":"2018-07-18","id":"DEN_LAX_2018-07-18_UA_815","month":7,"src":"DEN"}
{"arrdelay":4.0,"crsarrtime":750,"crsdephour":6,"crsdeptime":628,"crselapsedtime":202.0,"depdelay":14.0,"dist":1235.0,"fldate":"2018-07-18","id":"DFW_LAX_2018-07-18_UA_1216","month":7,"src":"DFW"}
{"arrdelay":0.0,"crsarrtime":2335,"crsdephour":20,"crsdeptime":2035,"crselapsedtime":360.0,"depdelay":0.0,"dist":2454.0,"fldate":"2018-07-18","id":"EWR_LAX_2018-07-18_UA_1141","month":7,"src":"EWR"}
{"arrdelay":0.0,"crsarrtime":1200,"crsdephour":9,"crsdeptime":915,"crselapsedtime":345.0,"depdelay":1.0,"dist":2454.0,"fldate":"2018-07-18","id":"EWR_LAX_2018-07-18_UA_1148","month":7,"src":"EWR"}
{"arrdelay":0.0,"crsarrtime":114,"crsdephour":22,"crsdeptime":2220,"crselapsedtime":354.0,"depdelay":0.0,"dist":2454.0,"fldate":"2018-07-18","id":"EWR_LAX_2018-07-18_UA_1165","month":7,"src":"EWR"}
{"arrdelay":0.0,"crsarrtime":2050,"crsdephour":17,"crsdeptime":1740,"crselapsedtime":370.0,"depdelay":14.0,"dist":2454.0,"fldate":"2018-07-18","id":"EWR_LAX_2018-07-18_UA_1600","month":7,"src":"EWR"}
{"arrdelay":0.0,"crsarrtime":1920,"crsdephour":16,"crsdeptime":1620,"crselapsedtime":360.0,"depdelay":0.0,"dist":2454.0,"fldate":"2018-07-18","id":"EWR_LAX_2018-07-18_UA_1871","month":7,"src":"EWR"}
{"arrdelay":0.0,"crsarrtime":1411,"crsdephour":11,"crsdeptime":1130,"crselapsedtime":341.0,"depdelay":0.0,"dist":2454.0,"fldate":"2018-07-18","id":"EWR_LAX_2018-07-18_UA_1960","month":7,"src":"EWR"}
{"arrdelay":12.0,"crsarrtime":1720,"crsdephour":14,"crsdeptime":1420,"crselapsedtime":360.0,"depdelay":32.0,"dist":2454.0,"fldate":"2018-07-18","id":"EWR_LAX_2018-07-18_UA_2394","month":7,"src":"EWR"}
{"arrdelay":0.0,"crsarrtime":2155,"crsdephour":19,"crsdeptime":1855,"crselapsedtime":360.0,"depdelay":0.0,"dist":2454.0,"fldate":"2018-07-18","id":"EWR_LAX_2018-07-18_UA_275","month":7,"src":"EWR"}
{"arrdelay":10.0,"crsarrtime":1125,"crsdephour":8,"crsdeptime":820,"crselapsedtime":365.0,"depdelay":1.0,"dist":2454.0,"fldate":"2018-07-18","id":"EWR_LAX_2018-07-18_UA_493","month":7,"src":"EWR"}
{"arrdelay":0.0,"crsarrtime":1041,"crsdephour":7,"crsdeptime":745,"crselapsedtime":356.0,"depdelay":0.0,"dist":2454.0,"fldate":"2018-07-18","id":"EWR_LAX_2018-07-18_UA_703","month":7,"src":"EWR"}
{"arrdelay":0.0,"crsarrtime":1840,"crsdephour":15,"crsdeptime":1530,"crselapsedtime":370.0,"depdelay":1.0,"dist":2454.0,"fldate":"2018-07-18","id":"EWR_LAX_2018-07-18_UA_751","month":7,"src":"EWR"}
{"arrdelay":0.0,"crsarrtime":856,"crsdephour":6,"crsdeptime":600,"crselapsedtime":356.0,"depdelay":0.0,"dist":2454.0,"fldate":"2018-07-18","id":"EWR_LAX_2018-07-18_UA_758","month":7,"src":"EWR"}
{"arrdelay":0.0,"crsarrtime":1336,"crsdephour":12,"crsdeptime":1215,"crselapsedtime":201.0,"depdelay":0.0,"dist":1379.0,"fldate":"2018-07-18","id":"IAH_LAX_2018-07-18_UA_1117","month":7,"src":"IAH"}
{"arrdelay":0.0,"crsarrtime":932,"crsdephour":8,"crsdeptime":754,"crselapsedtime":218.0,"depdelay":0.0,"dist":1379.0,"fldate":"2018-07-18","id":"IAH_LAX_2018-07-18_UA_1169","month":7,"src":"IAH"}
{"arrdelay":18.0,"crsarrtime":1801,"crsdephour":16,"crsdeptime":1630,"crselapsedtime":211.0,"depdelay":48.0,"dist":1379.0,"fldate":"2018-07-18","id":"IAH_LAX_2018-07-18_UA_1236","month":7,"src":"IAH"}
{"arrdelay":0.0,"crsarrtime":1621,"crsdephour":15,"crsdeptime":1450,"crselapsedtime":211.0,"depdelay":1.0,"dist":1379.0,"fldate":"2018-07-18","id":"IAH_LAX_2018-07-18_UA_1777","month":7,"src":"IAH"}
{"arrdelay":0.0,"crsarrtime":2055,"crsdephour":19,"crsdeptime":1927,"crselapsedtime":208.0,"depdelay":0.0,"dist":1379.0,"fldate":"2018-07-18","id":"IAH_LAX_2018-07-18_UA_1791","month":7,"src":"IAH"}
{"arrdelay":0.0,"crsarrtime":2255,"crsdephour":21,"crsdeptime":2131,"crselapsedtime":204.0,"depdelay":0.0,"dist":1379.0,"fldate":"2018-07-18","id":"IAH_LAX_2018-07-18_UA_1813","month":7,"src":"IAH"}
{"arrdelay":0.0,"crsarrtime":2137,"crsdephour":20,"crsdeptime":2004,"crselapsedtime":213.0,"depdelay":0.0,"dist":1379.0,"fldate":"2018-07-18","id":"IAH_LAX_2018-07-18_UA_1842","month":7,"src":"IAH"}
{"arrdelay":7.0,"crsarrtime":1111,"crsdephour":10,"crsdeptime":950,"crselapsedtime":201.0,"depdelay":11.0,"dist":1379.0,"fldate":"2018-07-18","id":"IAH_LAX_2018-07-18_UA_1956","month":7,"src":"IAH"}
{"arrdelay":24.0,"crsarrtime":1441,"crsdephour":13,"crsdeptime":1320,"crselapsedtime":201.0,"depdelay":47.0,"dist":1379.0,"fldate":"2018-07-18","id":"IAH_LAX_2018-07-18_UA_2097","month":7,"src":"IAH"}
{"arrdelay":0.0,"crsarrtime":708,"crsdephour":5,"crsdeptime":530,"crselapsedtime":218.0,"depdelay":0.0,"dist":1379.0,"fldate":"2018-07-18","id":"IAH_LAX_2018-07-18_UA_2382","month":7,"src":"IAH"}
{"arrdelay":0.0,"crsarrtime":1936,"crsdephour":18,"crsdeptime":1814,"crselapsedtime":202.0,"depdelay":4.0,"dist":1379.0,"fldate":"2018-07-18","id":"IAH_LAX_2018-07-18_UA_832","month":7,"src":"IAH"}
{"arrdelay":139.0,"crsarrtime":2330,"crsdephour":21,"crsdeptime":2110,"crselapsedtime":260.0,"depdelay":140.0,"dist":1744.0,"fldate":"2018-07-18","id":"ORD_LAX_2018-07-18_UA_1186","month":7,"src":"ORD"}
{"arrdelay":15.0,"crsarrtime":1025,"crsdephour":8,"crsdeptime":800,"crselapsedtime":265.0,"depdelay":0.0,"dist":1744.0,"fldate":"2018-07-18","id":"ORD_LAX_2018-07-18_UA_1489","month":7,"src":"ORD"}
{"arrdelay":0.0,"crsarrtime":1530,"crsdephour":13,"crsdeptime":1259,"crselapsedtime":271.0,"depdelay":0.0,"dist":1744.0,"fldate":"2018-07-18","id":"ORD_LAX_2018-07-18_UA_1536","month":7,"src":"ORD"}
{"arrdelay":0.0,"crsarrtime":1734,"crsdephour":15,"crsdeptime":1510,"crselapsedtime":264.0,"depdelay":0.0,"dist":1744.0,"fldate":"2018-07-18","id":"ORD_LAX_2018-07-18_UA_1836","month":7,"src":"ORD"}
{"arrdelay":0.0,"crsarrtime":900,"crsdephour":6,"crsdeptime":635,"crselapsedtime":265.0,"depdelay":0.0,"dist":1744.0,"fldate":"2018-07-18","id":"ORD_LAX_2018-07-18_UA_2194","month":7,"src":"ORD"}
{"arrdelay":0.0,"crsarrtime":1408,"crsdephour":11,"crsdeptime":1136,"crselapsedtime":272.0,"depdelay":0.0,"dist":1744.0,"fldate":"2018-07-18","id":"ORD_LAX_2018-07-18_UA_310","month":7,"src":"ORD"}
{"arrdelay":0.0,"crsarrtime":2015,"crsdephour":18,"crsdeptime":1755,"crselapsedtime":260.0,"depdelay":0.0,"dist":1744.0,"fldate":"2018-07-18","id":"ORD_LAX_2018-07-18_UA_369","month":7,"src":"ORD"}
{"arrdelay":6.0,"crsarrtime":2221,"crsdephour":20,"crsdeptime":1954,"crselapsedtime":267.0,"depdelay":0.0,"dist":1744.0,"fldate":"2018-07-18","id":"ORD_LAX_2018-07-18_UA_411","month":7,"src":"ORD"}
{"arrdelay":125.0,"crsarrtime":1232,"crsdephour":10,"crsdeptime":1012,"crselapsedtime":260.0,"depdelay":138.0,"dist":1744.0,"fldate":"2018-07-18","id":"ORD_LAX_2018-07-18_UA_531","month":7,"src":"ORD"}
{"arrdelay":0.0,"crsarrtime":1520,"crsdephour":12,"crsdeptime":1248,"crselapsedtime":272.0,"depdelay":0.0,"dist":1744.0,"fldate":"2018-07-18","id":"ORD_LAX_2018-07-18_UA_566","month":7,"src":"ORD"}
{"arrdelay":4.0,"crsarrtime":1820,"crsdephour":16,"crsdeptime":1600,"crselapsedtime":260.0,"depdelay":0.0,"dist":1744.0,"fldate":"2018-07-18","id":"ORD_LAX_2018-07-18_UA_592","month":7,"src":"ORD"}
{"arrdelay":0.0,"crsarrtime":124,"crsdephour":23,"crsdeptime":2305,"crselapsedtime":259.0,"depdelay":0.0,"dist":1744.0,"fldate":"2018-07-18","id":"ORD_LAX_2018-07-18_UA_683","month":7,"src":"ORD"}
{"arrdelay":25.0,"crsarrtime":1240,"crsdephour":11,"crsdeptime":1100,"crselapsedtime":100.0,"depdelay":45.0,"dist":337.0,"fldate":"2018-07-18","id":"SFO_LAX_2018-07-18_UA_1001","month":7,"src":"SFO"}
{"arrdelay":0.0,"crsarrtime":1542,"crsdephour":14,"crsdeptime":1400,"crselapsedtime":102.0,"depdelay":0.0,"dist":337.0,"fldate":"2018-07-18","id":"SFO_LAX_2018-07-18_UA_1248","month":7,"src":"SFO"}
{"arrdelay":0.0,"crsarrtime":1642,"crsdephour":15,"crsdeptime":1500,"crselapsedtime":102.0,"depdelay":1.0,"dist":337.0,"fldate":"2018-07-18","id":"SFO_LAX_2018-07-18_UA_207","month":7,"src":"SFO"}
{"arrdelay":19.0,"crsarrtime":1742,"crsdephour":16,"crsdeptime":1600,"crselapsedtime":102.0,"depdelay":0.0,"dist":337.0,"fldate":"2018-07-18","id":"SFO_LAX_2018-07-18_UA_215","month":7,"src":"SFO"}
{"arrdelay":0.0,"crsarrtime":2145,"crsdephour":20,"crsdeptime":2000,"crselapsedtime":105.0,"depdelay":0.0,"dist":337.0,"fldate":"2018-07-18","id":"SFO_LAX_2018-07-18_UA_2263","month":7,"src":"SFO"}
{"arrdelay":19.0,"crsarrtime":8,"crsdephour":22,"crsdeptime":2230,"crselapsedtime":98.0,"depdelay":13.0,"dist":337.0,"fldate":"2018-07-18","id":"SFO_LAX_2018-07-18_UA_257","month":7,"src":"SFO"}
{"arrdelay":6.0,"crsarrtime":734,"crsdephour":6,"crsdeptime":600,"crselapsedtime":94.0,"depdelay":0.0,"dist":337.0,"fldate":"2018-07-18","id":"SFO_LAX_2018-07-18_UA_261","month":7,"src":"SFO"}
{"arrdelay":15.0,"crsarrtime":1034,"crsdephour":9,"crsdeptime":900,"crselapsedtime":94.0,"depdelay":0.0,"dist":337.0,"fldate":"2018-07-18","id":"SFO_LAX_2018-07-18_UA_269","month":7,"src":"SFO"}
{"arrdelay":0.0,"crsarrtime":1435,"crsdephour":13,"crsdeptime":1300,"crselapsedtime":95.0,"depdelay":0.0,"dist":337.0,"fldate":"2018-07-18","id":"SFO_LAX_2018-07-18_UA_433","month":7,"src":"SFO"}
{"arrdelay":40.0,"crsarrtime":835,"crsdephour":7,"crsdeptime":700,"crselapsedtime":95.0,"depdelay":0.0,"dist":337.0,"fldate":"2018-07-18","id":"SFO_LAX_2018-07-18_UA_504","month":7,"src":"SFO"}
{"arrdelay":20.0,"crsarrtime":1842,"crsdephour":17,"crsdeptime":1700,"crselapsedtime":102.0,"depdelay":0.0,"dist":337.0,"fldate":"2018-07-18","id":"SFO_LAX_2018-07-18_UA_525","month":7,"src":"SFO"}
{"arrdelay":11.0,"crsarrtime":934,"crsdephour":8,"crsdeptime":800,"crselapsedtime":94.0,"depdelay":0.0,"dist":337.0,"fldate":"2018-07-18","id":"SFO_LAX_2018-07-18_UA_613","month":7,"src":"SFO"}
{"arrdelay":27.0,"crsarrtime":1135,"crsdephour":10,"crsdeptime":1000,"crselapsedtime":95.0,"depdelay":0.0,"dist":337.0,"fldate":"2018-07-18","id":"SFO_LAX_2018-07-18_UA_653","month":7,"src":"SFO"}
{"arrdelay":0.0,"crsarrtime":1942,"crsdephour":18,"crsdeptime":1800,"crselapsedtime":102.0,"depdelay":15.0,"dist":337.0,"fldate":"2018-07-18","id":"SFO_LAX_2018-07-18_UA_816","month":7,"src":"SFO"}
{"arrdelay":0.0,"crsarrtime":945,"crsdephour":6,"crsdeptime":625,"crselapsedtime":380.0,"depdelay":0.0,"dist":2611.0,"fldate":"2018-07-25","id":"BOS_LAX_2018-07-25_UA_1820","month":7,"src":"BOS"}
{"arrdelay":0.0,"crsarrtime":1235,"crsdephour":9,"crsdeptime":910,"crselapsedtime":385.0,"depdelay":0.0,"dist":2611.0,"fldate":"2018-07-25","id":"BOS_LAX_2018-07-25_UA_2145","month":7,"src":"BOS"}
{"arrdelay":0.0,"crsarrtime":2034,"crsdephour":17,"crsdeptime":1701,"crselapsedtime":393.0,"depdelay":4.0,"dist":2611.0,"fldate":"2018-07-25","id":"BOS_LAX_2018-07-25_UA_717","month":7,"src":"BOS"}
{"arrdelay":0.0,"crsarrtime":930,"crsdephour":8,"crsdeptime":758,"crselapsedtime":152.0,"depdelay":0.0,"dist":862.0,"fldate":"2018-07-25","id":"DEN_LAX_2018-07-25_UA_1093","month":7,"src":"DEN"}
{"arrdelay":0.0,"crsarrtime":2020,"crsdephour":19,"crsdeptime":1855,"crselapsedtime":145.0,"depdelay":0.0,"dist":862.0,"fldate":"2018-07-25","id":"DEN_LAX_2018-07-25_UA_1613","month":7,"src":"DEN"}
{"arrdelay":4.0,"crsarrtime":1409,"crsdephour":12,"crsdeptime":1244,"crselapsedtime":145.0,"depdelay":5.0,"dist":862.0,"fldate":"2018-07-25","id":"DEN_LAX_2018-07-25_UA_2091","month":7,"src":"DEN"}
{"arrdelay":0.0,"crsarrtime":708,"crsdephour":5,"crsdeptime":545,"crselapsedtime":143.0,"depdelay":0.0,"dist":862.0,"fldate":"2018-07-25","id":"DEN_LAX_2018-07-25_UA_2186","month":7,"src":"DEN"}
{"arrdelay":2.0,"crsarrtime":1239,"crsdephour":11,"crsdeptime":1115,"crselapsedtime":144.0,"depdelay":3.0,"dist":862.0,"fldate":"2018-07-25","id":"DEN_LAX_2018-07-25_UA_420","month":7,"src":"DEN"}
{"arrdelay":16.0,"crsarrtime":1703,"crsdephour":15,"crsdeptime":1535,"crselapsedtime":148.0,"depdelay":0.0,"dist":862.0,"fldate":"2018-07-25","id":"DEN_LAX_2018-07-25_UA_481","month":7,"src":"DEN"}
{"arrdelay":0.0,"crsarrtime":1540,"crsdephour":14,"crsdeptime":1415,"crselapsedtime":145.0,"depdelay":0.0,"dist":862.0,"fldate":"2018-07-25","id":"DEN_LAX_2018-07-25_UA_744","month":7,"src":"DEN"}
{"arrdelay":11.0,"crsarrtime":13,"crsdephour":23,"crsdeptime":2250,"crselapsedtime":143.0,"depdelay":7.0,"dist":862.0,"fldate":"2018-07-25","id":"DEN_LAX_2018-07-25_UA_815","month":7,"src":"DEN"}
{"arrdelay":0.0,"crsarrtime":750,"crsdephour":6,"crsdeptime":628,"crselapsedtime":202.0,"depdelay":0.0,"dist":1235.0,"fldate":"2018-07-25","id":"DFW_LAX_2018-07-25_UA_1216","month":7,"src":"DFW"}
{"arrdelay":67.0,"crsarrtime":2335,"crsdephour":20,"crsdeptime":2035,"crselapsedtime":360.0,"depdelay":70.0,"dist":2454.0,"fldate":"2018-07-25","id":"EWR_LAX_2018-07-25_UA_1141","month":7,"src":"EWR"}
{"arrdelay":8.0,"crsarrtime":1200,"crsdephour":9,"crsdeptime":915,"crselapsedtime":345.0,"depdelay":11.0,"dist":2454.0,"fldate":"2018-07-25","id":"EWR_LAX_2018-07-25_UA_1148","month":7,"src":"EWR"}
{"arrdelay":100.0,"crsarrtime":114,"crsdephour":22,"crsdeptime":2220,"crselapsedtime":354.0,"depdelay":127.0,"dist":2454.0,"fldate":"2018-07-25","id":"EWR_LAX_2018-07-25_UA_1165","month":7,"src":"EWR"}
{"arrdelay":66.0,"crsarrtime":2050,"crsdephour":17,"crsdeptime":1740,"crselapsedtime":370.0,"depdelay":60.0,"dist":2454.0,"fldate":"2018-07-25","id":"EWR_LAX_2018-07-25_UA_1600","month":7,"src":"EWR"}
{"arrdelay":0.0,"crsarrtime":1920,"crsdephour":16,"crsdeptime":1620,"crselapsedtime":360.0,"depdelay":0.0,"dist":2454.0,"fldate":"2018-07-25","id":"EWR_LAX_2018-07-25_UA_1871","month":7,"src":"EWR"}
{"arrdelay":2.0,"crsarrtime":1411,"crsdephour":11,"crsdeptime":1130,"crselapsedtime":341.0,"depdelay":13.0,"dist":2454.0,"fldate":"2018-07-25","id":"EWR_LAX_2018-07-25_UA_1960","month":7,"src":"EWR"}
{"arrdelay":8.0,"crsarrtime":1720,"crsdephour":14,"crsdeptime":1420,"crselapsedtime":360.0,"depdelay":27.0,"dist":2454.0,"fldate":"2018-07-25","id":"EWR_LAX_2018-07-25_UA_2394","month":7,"src":"EWR"}
{"arrdelay":96.0,"crsarrtime":2155,"crsdephour":19,"crsdeptime":1855,"crselapsedtime":360.0,"depdelay":98.0,"dist":2454.0,"fldate":"2018-07-25","id":"EWR_LAX_2018-07-25_UA_275","month":7,"src":"EWR"}
{"arrdelay":101.0,"crsarrtime":1125,"crsdephour":8,"crsdeptime":820,"crselapsedtime":365.0,"depdelay":133.0,"dist":2454.0,"fldate":"2018-07-25","id":"EWR_LAX_2018-07-25_UA_493","month":7,"src":"EWR"}
{"arrdelay":71.0,"crsarrtime":1041,"crsdephour":7,"crsdeptime":745,"crselapsedtime":356.0,"depdelay":20.0,"dist":2454.0,"fldate":"2018-07-25","id":"EWR_LAX_2018-07-25_UA_703","month":7,"src":"EWR"}
{"arrdelay":0.0,"crsarrtime":1840,"crsdephour":15,"crsdeptime":1530,"crselapsedtime":370.0,"depdelay":0.0,"dist":2454.0,"fldate":"2018-07-25","id":"EWR_LAX_2018-07-25_UA_751","month":7,"src":"EWR"}
{"arrdelay":0.0,"crsarrtime":856,"crsdephour":6,"crsdeptime":600,"crselapsedtime":356.0,"depdelay":0.0,"dist":2454.0,"fldate":"2018-07-25","id":"EWR_LAX_2018-07-25_UA_758","month":7,"src":"EWR"}
{"arrdelay":0.0,"crsarrtime":1336,"crsdephour":12,"crsdeptime":1215,"crselapsedtime":201.0,"depdelay":0.0,"dist":1379.0,"fldate":"2018-07-25","id":"IAH_LAX_2018-07-25_UA_1117","month":7,"src":"IAH"}
{"arrdelay":0.0,"crsarrtime":932,"crsdephour":8,"crsdeptime":754,"crselapsedtime":218.0,"depdelay":0.0,"dist":1379.0,"fldate":"2018-07-25","id":"IAH_LAX_2018-07-25_UA_1169","month":7,"src":"IAH"}
{"arrdelay":0.0,"crsarrtime":1801,"crsdephour":16,"crsdeptime":1630,"crselapsedtime":211.0,"depdelay":0.0,"dist":1379.0,"fldate":"2018-07-25","id":"IAH_LAX_2018-07-25_UA_1236","month":7,"src":"IAH"}
{"arrdelay":11.0,"crsarrtime":1621,"crsdephour":15,"crsdeptime":1450,"crselapsedtime":211.0,"depdelay":29.0,"dist":1379.0,"fldate":"2018-07-25","id":"IAH_LAX_2018-07-25_UA_1777","month":7,"src":"IAH"}
{"arrdelay":3.0,"crsarrtime":2055,"crsdephour":19,"crsdeptime":1927,"crselapsedtime":208.0,"depdelay":24.0,"dist":1379.0,"fldate":"2018-07-25","id":"IAH_LAX_2018-07-25_UA_1791","month":7,"src":"IAH"}
{"arrdelay":6.0,"crsarrtime":2255,"crsdephour":21,"crsdeptime":2131,"crselapsedtime":204.0,"depdelay":11.0,"dist":1379.0,"fldate":"2018-07-25","id":"IAH_LAX_2018-07-25_UA_1813","month":7,"src":"IAH"}
{"arrdelay":7.0,"crsarrtime":2137,"crsdephour":20,"crsdeptime":2004,"crselapsedtime":213.0,"depdelay":23.0,"dist":1379.0,"fldate":"2018-07-25","id":"IAH_LAX_2018-07-25_UA_1842","month":7,"src":"IAH"}
{"arrdelay":41.0,"crsarrtime":1111,"crsdephour":10,"crsdeptime":950,"crselapsedtime":201.0,"depdelay":49.0,"dist":1379.0,"fldate":"2018-07-25","id":"IAH_LAX_2018-07-25_UA_1956","month":7,"src":"IAH"}
{"arrdelay":0.0,"crsarrtime":1441,"crsdephour":13,"crsdeptime":1320,"crselapsedtime":201.0,"depdelay":15.0,"dist":1379.0,"fldate":"2018-07-25","id":"IAH_LAX_2018-07-25_UA_2097","month":7,"src":"IAH"}
{"arrdelay":0.0,"crsarrtime":708,"crsdephour":5,"crsdeptime":530,"crselapsedtime":218.0,"depdelay":0.0,"dist":1379.0,"fldate":"2018-07-25","id":"IAH_LAX_2018-07-25_UA_2382","month":7,"src":"IAH"}
{"arrdelay":0.0,"crsarrtime":1936,"crsdephour":18,"crsdeptime":1814,"crselapsedtime":202.0,"depdelay":2.0,"dist":1379.0,"fldate":"2018-07-25","id":"IAH_LAX_2018-07-25_UA_832","month":7,"src":"IAH"}
{"arrdelay":0.0,"crsarrtime":2330,"crsdephour":21,"crsdeptime":2110,"crselapsedtime":260.0,"depdelay":0.0,"dist":1744.0,"fldate":"2018-07-25","id":"ORD_LAX_2018-07-25_UA_1186","month":7,"src":"ORD"}
{"arrdelay":10.0,"crsarrtime":1025,"crsdephour":8,"crsdeptime":800,"crselapsedtime":265.0,"depdelay":0.0,"dist":1744.0,"fldate":"2018-07-25","id":"ORD_LAX_2018-07-25_UA_1489","month":7,"src":"ORD"}
{"arrdelay":0.0,"crsarrtime":1530,"crsdephour":13,"crsdeptime":1259,"crselapsedtime":271.0,"depdelay":0.0,"dist":1744.0,"fldate":"2018-07-25","id":"ORD_LAX_2018-07-25_UA_1536","month":7,"src":"ORD"}
{"arrdelay":5.0,"crsarrtime":1749,"crsdephour":15,"crsdeptime":1525,"crselapsedtime":264.0,"depdelay":23.0,"dist":1744.0,"fldate":"2018-07-25","id":"ORD_LAX_2018-07-25_UA_1836","month":7,"src":"ORD"}
{"arrdelay":0.0,"crsarrtime":900,"crsdephour":6,"crsdeptime":635,"crselapsedtime":265.0,"depdelay":0.0,"dist":1744.0,"fldate":"2018-07-25","id":"ORD_LAX_2018-07-25_UA_2194","month":7,"src":"ORD"}
{"arrdelay":0.0,"crsarrtime":1408,"crsdephour":11,"crsdeptime":1136,"crselapsedtime":272.0,"depdelay":0.0,"dist":1744.0,"fldate":"2018-07-25","id":"ORD_LAX_2018-07-25_UA_310","month":7,"src":"ORD"}
{"arrdelay":0.0,"crsarrtime":2015,"crsdephour":18,"crsdeptime":1755,"crselapsedtime":260.0,"depdelay":0.0,"dist":1744.0,"fldate":"2018-07-25","id":"ORD_LAX_2018-07-25_UA_369","month":7,"src":"ORD"}
{"arrdelay":0.0,"crsarrtime":2221,"crsdephour":20,"crsdeptime":1954,"crselapsedtime":267.0,"depdelay":0.0,"dist":1744.0,"fldate":"2018-07-25","id":"ORD_LAX_2018-07-25_UA_411","month":7,"src":"ORD"}
{"arrdelay":160.0,"crsarrtime":1232,"crsdephour":10,"crsdeptime":1012,"crselapsedtime":260.0,"depdelay":169.0,"dist":1744.0,"fldate":"2018-07-25","id":"ORD_LAX_2018-07-25_UA_531","month":7,"src":"ORD"}
{"arrdelay":80.0,"crsarrtime":1520,"crsdephour":12,"crsdeptime":1248,"crselapsedtime":272.0,"depdelay":91.0,"dist":1744.0,"fldate":"2018-07-25","id":"ORD_LAX_2018-07-25_UA_566","month":7,"src":"ORD"}
{"arrdelay":20.0,"crsarrtime":1820,"crsdephour":16,"crsdeptime":1600,"crselapsedtime":260.0,"depdelay":0.0,"dist":1744.0,"fldate":"2018-07-25","id":"ORD_LAX_2018-07-25_UA_592","month":7,"src":"ORD"}
{"arrdelay":0.0,"crsarrtime":124,"crsdephour":23,"crsdeptime":2305,"crselapsedtime":259.0,"depdelay":0.0,"dist":1744.0,"fldate":"2018-07-25","id":"ORD_LAX_2018-07-25_UA_683","month":7,"src":"ORD"}
{"arrdelay":0.0,"crsarrtime":1240,"crsdephour":11,"crsdeptime":1100,"crselapsedtime":100.0,"depdelay":8.0,"dist":337.0,"fldate":"2018-07-25","id":"SFO_LAX_2018-07-25_UA_1001","month":7,"src":"SFO"}
{"arrdelay":0.0,"crsarrtime":1542,"crsdephour":14,"crsdeptime":1400,"crselapsedtime":102.0,"depdelay":0.0,"dist":337.0,"fldate":"2018-07-25","id":"SFO_LAX_2018-07-25_UA_1248","month":7,"src":"SFO"}
{"arrdelay":0.0,"crsarrtime":1642,"crsdephour":15,"crsdeptime":1500,"crselapsedtime":102.0,"depdelay":0.0,"dist":337.0,"fldate":"2018-07-25","id":"SFO_LAX_2018-07-25_UA_207","month":7,"src":"SFO"}
{"arrdelay":8.0,"crsarrtime":1742,"crsdephour":16,"crsdeptime":1600,"crselapsedtime":102.0,"depdelay":0.0,"dist":337.0,"fldate":"2018-07-25","id":"SFO_LAX_2018-07-25_UA_215","month":7,"src":"SFO"}
{"arrdelay":70.0,"crsarrtime":2145,"crsdephour":20,"crsdeptime":2000,"crselapsedtime":105.0,"depdelay":75.0,"dist":337.0,"fldate":"2018-07-25","id":"SFO_LAX_2018-07-25_UA_2263","month":7,"src":"SFO"}
{"arrdelay":0.0,"crsarrtime":8,"crsdephour":22,"crsdeptime":2230,"crselapsedtime":98.0,"depdelay":0.0,"dist":337.0,"fldate":"2018-07-25","id":"SFO_LAX_2018-07-25_UA_257","month":7,"src":"SFO"}
{"arrdelay":0.0,"crsarrtime":734,"crsdephour":6,"crsdeptime":600,"crselapsedtime":94.0,"depdelay":0.0,"dist":337.0,"fldate":"2018-07-25","id":"SFO_LAX_2018-07-25_UA_261","month":7,"src":"SFO"}
{"arrdelay":5.0,"crsarrtime":1034,"crsdephour":9,"crsdeptime":900,"crselapsedtime":94.0,"depdelay":0.0,"dist":337.0,"fldate":"2018-07-25","id":"SFO_LAX_2018-07-25_UA_269","month":7,"src":"SFO"}
{"arrdelay":5.0,"crsarrtime":1435,"crsdephour":13,"crsdeptime":1300,"crselapsedtime":95.0,"depdelay":0.0,"dist":337.0,"fldate":"2018-07-25","id":"SFO_LAX_2018-07-25_UA_433","month":7,"src":"SFO"}
{"arrdelay":4.0,"crsarrtime":835,"crsdephour":7,"crsdeptime":700,"crselapsedtime":95.0,"depdelay":0.0,"dist":337.0,"fldate":"2018-07-25","id":"SFO_LAX_2018-07-25_UA_504","month":7,"src":"SFO"}
{"arrdelay":0.0,"crsarrtime":1842,"crsdephour":17,"crsdeptime":1700,"crselapsedtime":102.0,"depdelay":0.0,"dist":337.0,"fldate":"2018-07-25","id":"SFO_LAX_2018-07-25_UA_525","month":7,"src":"SFO"}
{"arrdelay":1.0,"crsarrtime":934,"crsdephour":8,"crsdeptime":800,"crselapsedtime":94.0,"depdelay":0.0,"dist":337.0,"fldate":"2018-07-25","id":"SFO_LAX_2018-07-25_UA_613","month":7,"src":"SFO"}
{"arrdelay":11.0,"crsarrtime":1135,"crsdephour":10,"crsdeptime":1000,"crselapsedtime":95.0,"depdelay":0.0,"dist":337.0,"fldate":"2018-07-25","id":"SFO_LAX_2018-07-25_UA_653","month":7,"src":"SFO"}
{"arrdelay":0.0,"crsarrtime":1942,"crsdephour":18,"crsdeptime":1800,"crselapsedtime":102.0,"depdelay":0.0,"dist":337.0,"fldate":"2018-07-25","id":"SFO_LAX_2018-07-25_UA_816","month":7,"src":"SFO"}
